pydnn/aws_util.py
pydnn/data.py
pydnn/tools.py
pydnn/preprocess.py
pydnn/nn.py
pydnn/__init__.py
pydnn/img_util.py
examples/__init__.py
examples/plankton/__init__.py
examples/plankton/plankton.py
examples/plankton/experiment.py
pydnn-0.0.dev.dist-info/RECORD
pydnn-0.0.dev.dist-info/WHEEL
pydnn-0.0.dev.dist-info/metadata.json
pydnn-0.0.dev.dist-info/DESCRIPTION.rst
pydnn-0.0.dev.dist-info/METADATA
pydnn-0.0.dev.dist-info/top_level.txt
