Metadata-Version: 2.0
Name: pydnn
Version: 0.0.dev
Summary: deep neural network library in Python
Home-page: https://github.com/zackriegman/pydnn
Author: Isaac Kriegman
Author-email: zackriegman@gmail.com
License: MIT
Keywords: neural network deep learning AI machine learning
Platform: UNKNOWN
Classifier: Development Status :: 2 - Pre-Alpha
Classifier: Programming Language :: Python :: 2.7
Classifier: Programming Language :: Python :: 3.4
Classifier: License :: OSI Approved :: MIT License
Classifier: Environment :: Console
Classifier: Intended Audience :: Science/Research
Classifier: Intended Audience :: Developers
Classifier: Intended Audience :: Education
Classifier: Intended Audience :: End Users/Desktop
Classifier: Topic :: Scientific/Engineering :: Artificial Intelligence
Classifier: Topic :: Scientific/Engineering :: Image Recognition
Classifier: Topic :: Scientific/Engineering :: Information Analysis
Classifier: Topic :: Software Development :: Libraries
Requires-Dist: numpy
Requires-Dist: scipy
Requires-Dist: Theano (>=0.7.0rc1.dev)
Requires-Dist: pyyaml
Requires-Dist: boto
Requires-Dist: pandas
Provides-Extra: docs
Requires-Dist: Sphinx; extra == 'docs'
